schema_models/User.py
schema_models/__init__.py
schema_models/chat.py
workversegame_schema_models-1.0.14.dist-info/METADATA
workversegame_schema_models-1.0.14.dist-info/WHEEL
workversegame_schema_models-1.0.14.dist-info/top_level.txt
workversegame_schema_models-1.0.14.dist-info/RECORD
