Metadata-Version: 2.4
Name: workversegame_schema_models
Version: 1.0.14
Summary: Auto-generated Python database models from JSON schemas
Author: WorkverseGame
Author-email: your-email@example.com
Classifier: Programming Language :: Python :: 3
Classifier: License :: OSI Approved :: MIT License
Classifier: Operating System :: OS Independent
Requires-Python: >=3.6
Requires-Dist: pydantic>=1.8.0
Dynamic: author
Dynamic: author-email
Dynamic: classifier
Dynamic: requires-dist
Dynamic: requires-python
Dynamic: summary
